switch_hub/__init__.py
switch_hub/helpers.py
switch_hub/logger.py
switch_hub/main.py
switch_hub-0.0.5.dist-info/METADATA
switch_hub-0.0.5.dist-info/WHEEL
switch_hub-0.0.5.dist-info/licenses/LICENSE
switch_hub-0.0.5.dist-info/RECORD
