Metadata-Version: 2.4
Name: switch_hub
Version: 0.0.5
Summary: Toggle Huggingface Hub and Cloud.ru Repo
Project-URL: Homepage, https://github.com/Gravi7ON/switch-hub
Project-URL: Issues, https://github.com/Gravi7ON/switch-hub/issues
Author-email: Dmitry Radionov <radionovdmr@gmail.com>
License-File: LICENSE
Classifier: License :: OSI Approved :: MIT License
Classifier: Operating System :: OS Independent
Classifier: Programming Language :: Python :: 3
Requires-Python: >=3.9.6
Requires-Dist: datasets==4.0.0
Requires-Dist: huggingface-hub==0.33.4
Requires-Dist: python-dotenv==1.1.1
